microgen/__init__.py
microgen/cli.py
microgen/constants.py
microgen/generators.py
microgen/other.md
microgen/templates/__init__.py
microgen/templates/root_templates.py
microgen/templates/service_templates.py
rishram_microgen-4.0.1.dist-info/METADATA
rishram_microgen-4.0.1.dist-info/WHEEL
rishram_microgen-4.0.1.dist-info/entry_points.txt
rishram_microgen-4.0.1.dist-info/top_level.txt
rishram_microgen-4.0.1.dist-info/RECORD
