Metadata-Version: 2.4
Name: rishram-microgen
Version: 4.0.1
Summary: Microservice folder generator
Author-email: Ujjwal Rana <ujjwalr754@gmail.com>
Requires-Python: >=3.8
Requires-Dist: click
